py21cmmc/__init__.py
py21cmmc/_utils.py
py21cmmc/analyse.py
py21cmmc/core.py
py21cmmc/cosmoHammer.py
py21cmmc/ensemble.py
py21cmmc/likelihood.py
py21cmmc/mcmc.py
py21cmmc/__pycache__/__init__.cpython-37.pyc
py21cmmc/__pycache__/_utils.cpython-37.pyc
py21cmmc/__pycache__/analyse.cpython-37.pyc
py21cmmc/__pycache__/core.cpython-37.pyc
py21cmmc/__pycache__/cosmoHammer.cpython-37.pyc
py21cmmc/__pycache__/ensemble.cpython-37.pyc
py21cmmc/__pycache__/likelihood.cpython-37.pyc
py21cmmc/__pycache__/mcmc.cpython-37.pyc
py21cmmc/data/LF_lfuncs_z10.npz
py21cmmc/data/LF_lfuncs_z6.npz
py21cmmc/data/LF_lfuncs_z7.npz
py21cmmc/data/LF_lfuncs_z8.npz
py21cmmc/data/LF_sigmas_z10.npz
py21cmmc/data/LF_sigmas_z6.npz
py21cmmc/data/LF_sigmas_z7.npz
py21cmmc/data/LF_sigmas_z8.npz
py21cmmc/data/NeutralFractionPDF_SmallHII.npy
py21cmmc/data/NeutralFractionPDF_SmallHII.out
py21cmmc/data/NeutralFractionsForPDF.npy
py21cmmc/data/NeutralFractionsForPDF.out
21CMMC-1.0.0.dev3.dist-info/AUTHORS.rst
21CMMC-1.0.0.dev3.dist-info/LICENSE
21CMMC-1.0.0.dev3.dist-info/METADATA
21CMMC-1.0.0.dev3.dist-info/WHEEL
21CMMC-1.0.0.dev3.dist-info/top_level.txt
21CMMC-1.0.0.dev3.dist-info/RECORD
