Metadata-Version: 2.1
Name: 21CMMC
Version: 1.0.0.dev3
Summary: An extensible MCMC framework for 21cmFAST
Home-page: https://github.com/21cmFAST/21CMMC
Author: Brad Greig
Author-email: greigb@unimelb.edu.au
License: MIT license
Keywords: Epoch of Reionization,Cosmology
Platform: UNKNOWN
Classifier: Development Status :: 5 - Production/Stable
Classifier: Intended Audience :: Developers
Classifier: License :: OSI Approved :: MIT License
Classifier: Operating System :: Unix
Classifier: Operating System :: POSIX
Classifier: Programming Language :: Python
Classifier: Programming Language :: Python :: 3
Classifier: Programming Language :: Python :: 3.6
Classifier: Programming Language :: Python :: 3.7
Classifier: Programming Language :: Python :: Implementation :: CPython
Requires-Dist: click
Requires-Dist: numpy
Requires-Dist: cosmoHammer
Requires-Dist: scipy
Requires-Dist: matplotlib (>=2.1)
Requires-Dist: emcee (<3)
Requires-Dist: powerbox (>=0.5.7)
Requires-Dist: cached-property
Requires-Dist: 21cmFAST (>=3.0.0dev1)
Requires-Dist: pymultinest
Provides-Extra: samplers
Requires-Dist: pymultinest ; extra == 'samplers'
